__init__.py
exam2excel_converter.py
test.py
Exam2excel_converter-0.0.2.dist-info/LICENSE
Exam2excel_converter-0.0.2.dist-info/METADATA
Exam2excel_converter-0.0.2.dist-info/WHEEL
Exam2excel_converter-0.0.2.dist-info/top_level.txt
Exam2excel_converter-0.0.2.dist-info/RECORD
