Metadata-Version: 2.1
Name: Exam2excel-converter
Version: 0.0.2
Summary: Tool convert question of exam to excel
Author-email: akakshuki <le.dinhhoang.1207@gmail.com>
Classifier: Programming Language :: Python :: 3
Classifier: License :: OSI Approved :: MIT License
Classifier: Operating System :: OS Independent
Requires-Python: >=3.7
License-File: LICENSE
